lingoshelle/__init__.py
lingoshelle/__main__.py
lingoshelle/installer.py
lingoshelle-1.4.dist-info/METADATA
lingoshelle-1.4.dist-info/WHEEL
lingoshelle-1.4.dist-info/entry_points.txt
lingoshelle-1.4.dist-info/top_level.txt
lingoshelle-1.4.dist-info/RECORD
