Metadata-Version: 2.1
Name: lingoshelle
Version: 1.4
Requires-Dist: requests>=2.25.0
Requires-Dist: openai>=0.27.0
Requires-Dist: python-dotenv>=0.19.0
Requires-Dist: pyyaml>=5.4.1
Requires-Dist: pyperclip>=1.8.2
Requires-Dist: termcolor>=1.1.0
Requires-Dist: colorama>=0.4.4
Requires-Dist: aiohttp>=3.7.4
Requires-Dist: keyring>=23.2.1
Requires-Dist: urllib3>=1.26.6
